README.md
setup.cfg
setup.py
jg_distributions/Binomialdistribution.py
jg_distributions/Gaussiandistribution.py
jg_distributions/Generaldistribution.py
jg_distributions/__init__.py
jg_distributions.egg-info/PKG-INFO
jg_distributions.egg-info/SOURCES.txt
jg_distributions.egg-info/dependency_links.txt
jg_distributions.egg-info/not-zip-safe
jg_distributions.egg-info/top_level.txt