Metadata-Version: 1.0
Name: jg-distributions
Version: 0.1
Summary: Gaussian distributions
Home-page: UNKNOWN
Author: Toure Lee
Author-email: movieduh@gmail.com
License: UNKNOWN
Platform: UNKNOWN
